maxlog.py
maxlog-0.2.0.dist-info/WHEEL
maxlog-0.2.0.dist-info/METADATA
maxlog-0.2.0.dist-info/RECORD
