Metadata-Version: 2.1
Name: maxlog
Version: 0.2.0
Summary: Helper module for logging using Loguru sinks.
License: MIT
Author: maxludden
Author-email: dev@maxludden.com
Requires-Python: >=3.10,<4.0
Classifier: License :: OSI Approved :: MIT License
Classifier: Programming Language :: Python :: 3
Classifier: Programming Language :: Python :: 3.10
Classifier: Programming Language :: Python :: 3.11
Requires-Dist: loguru (>=0.6.0,<0.7.0)
Requires-Dist: maxcolor (>=1.0.0,<2.0.0)
Requires-Dist: maxconsole (>=0.4.0,<0.5.0)
Requires-Dist: maxprogress (>=0.4.0,<0.5.0)
Requires-Dist: myaml (>=1.0.1,<2.0.0)
Requires-Dist: rich[all] (>=12.6.0,<13.0.0)
